README.rst
setup.cfg
setup.py
att_bill_splitter.egg-info/PKG-INFO
att_bill_splitter.egg-info/SOURCES.txt
att_bill_splitter.egg-info/dependency_links.txt
att_bill_splitter.egg-info/entry_points.txt
att_bill_splitter.egg-info/not-zip-safe
att_bill_splitter.egg-info/requires.txt
att_bill_splitter.egg-info/top_level.txt
attbillsplitter/__init__.py
attbillsplitter/entrypoints.py
attbillsplitter/errors.py
attbillsplitter/main.py
attbillsplitter/models.py
attbillsplitter/services.py
attbillsplitter/tests.py
attbillsplitter/utils.py