Metadata-Version: 1.0
Name: att-bill-splitter
Version: 0.4.6
Summary: Parse AT&T bill and split wireless charges among users.
Home-page: https://github.com/brianzq/att-bill-splitter
Author: Brian Zhang
Author-email: leapingzhang@gmail.com
License: UNKNOWN
Platform: UNKNOWN
